README.md
setup.py
chiaoupload/__init__.py
chiaoupload/hello.py
chiaoupload.egg-info/PKG-INFO
chiaoupload.egg-info/SOURCES.txt
chiaoupload.egg-info/dependency_links.txt
chiaoupload.egg-info/top_level.txt