Metadata-Version: 1.1
Name: chiaoupload
Version: 0.0.3
Summary: test upload package
Home-page: https://github.com/luckchiao
Author: chiao
Author-email: luckchiao@gmail.com
License: UNKNOWN
Keywords: python
Platform: UNKNOWN
Classifier: Development Status :: 3 - Alpha
Classifier: Intended Audience :: Developers
Classifier: Topic :: Software Development :: Build Tools
Classifier: License :: OSI Approved :: MIT License
Classifier: Programming Language :: Python :: 3.6
